hybrid_compute_sdk/__init__.py
hybrid_compute_sdk/server.py
hybrid_compute_sdk-0.2.43.dist-info/METADATA
hybrid_compute_sdk-0.2.43.dist-info/WHEEL
hybrid_compute_sdk-0.2.43.dist-info/top_level.txt
hybrid_compute_sdk-0.2.43.dist-info/RECORD
